{
  "gold_news_2026-06-17_13": true,
  "gold_news_2026-06-17_16": true,
  "daily_gold_bias_2026-06-17": true,
  "gold_news_2026-06-17_22": true,
  "gold_news_2026-06-18_10": true,
  "gold_news_2026-06-18_11": true,
  "gold_news_2026-06-18_12": true,
  "gold_news_2026-06-18_13": true,
  "gold_news_2026-06-18_14": true,
  "gold_news_2026-06-18_15": true,
  "last_bias_score": -6,
  "last_daily_total_score": -6,
  "daily_gold_bias_2026-06-19": true,
  "session_report_TEST PHIÊN_2026-06-19_11": true,
  "session_report_TEST PHIÊN_2026-06-19_12": true,
  "session_report_TEST DEBUG_2026-06-19_12": true,
  "session_report_TEST 999_2026-06-19_12": true,
  "session_report_TEST 999_2026-06-19_13": true,
  "session_report_TEST 999_2026-06-19_14": true,
  "session_report_TEST TREND_2026-06-19_16": true,
  "session_report_TEST TREND_2026-06-19_18": true,
  "session_report_TEST TREND_2026-06-19_19": true,
  "session_report_PHIÊN MỸ_2026-06-19_21": true,
  "session_report_TEST TREND_2026-06-19_21": true,
  "session_report_TEST TREND_2026-06-19": true,
  "session_report_PHIÊN MỸ_2026-06-19": true,
  "daily_gold_bias_2026-06-20": true,
  "no_news_2026-06-20": true,
  "daily_2026-06-20": true,
  "daily_gold_bias_2026-06-21": true,
  "session_report_PHIÊN Á_2026-06-21": true,
  "weekend_notice_2026-06-21": true,
  "daily_gold_bias_2026-06-22": true,
  "daily_gold_bias_2026-06-23": true,
  "daily_gold_bias_2026-06-24": true,
  "daily_2026-06-24": true,
  "daily_gold_bias_2026-06-25": true,
  "daily_2026-06-25": true,
  "daily_all_events_2026-06-25": true
}